super_selfish/__init__.py
super_selfish/data.py
super_selfish/memory.py
super_selfish/models.py
super_selfish/perms.py
super_selfish/supervisors.py
super_selfish/utils.py
super_selfish/efficientnet_pytorch/__init__.py
super_selfish/efficientnet_pytorch/model.py
super_selfish/efficientnet_pytorch/utils.py
super_selfish-0.0.6.dist-info/METADATA
super_selfish-0.0.6.dist-info/WHEEL
super_selfish-0.0.6.dist-info/top_level.txt
super_selfish-0.0.6.dist-info/RECORD
