Metadata-Version: 2.1
Name: super-selfish
Version: 0.0.6
Summary: A self-supervision PyTorch framework
Home-page: https://github.com/nwWag/Super-Selfish
Author: Nicolas Wagner
Author-email: nicolas_wagner@gmx.de
License: UNKNOWN
Platform: UNKNOWN
Classifier: Programming Language :: Python :: 3
Classifier: Operating System :: OS Independent
Requires-Python: >=3.6
